rp_compression/__init__.py
rp_compression/rp_compression.py
tests/__init__.py
tests/test.py
rp_compression-0.0.3.dist-info/LICENSE
rp_compression-0.0.3.dist-info/METADATA
rp_compression-0.0.3.dist-info/WHEEL
rp_compression-0.0.3.dist-info/top_level.txt
rp_compression-0.0.3.dist-info/RECORD
