Metadata-Version: 2.1
Name: rp-compression
Version: 0.0.3
Summary: gradient compression with random projection
Home-page: https://github.com/ElvinKim/rp_compression
Author: SangMook Kim
Author-email: sangmook.kim@kaist.ac.kr
License: UNKNOWN
Keywords: gradient,compression,random,projection
Platform: UNKNOWN
Classifier: License :: OSI Approved :: MIT License
Requires-Python: >=3
Requires-Dist: torch
Requires-Dist: numpy
